sounder/__init__.py
sounder/sounder.py
sounder-0.2.0.dist-info/DESCRIPTION.rst
sounder-0.2.0.dist-info/METADATA
sounder-0.2.0.dist-info/RECORD
sounder-0.2.0.dist-info/WHEEL
sounder-0.2.0.dist-info/metadata.json
sounder-0.2.0.dist-info/top_level.txt
