Metadata-Version: 1.1
Name: sounder
Version: 0.2.0
Summary: An intent recognition algorithm.
Home-page: https://github.com/slapbot/sounder
Author: Ujjwal Gupta
Author-email: ugupta41@gmail.com
License: MIT
Keywords: intent recognition munkres levenshtein edit-distance algorithm speech pattern sentiment analysis guess text
Platform: UNKNOWN
Classifier: Development Status :: 3 - Alpha
Classifier: Environment :: Web Environment
Classifier: Operating System :: OS Independent
Classifier: Intended Audience :: Developers
Classifier: Topic :: Software Development :: Build Tools
Classifier: License :: OSI Approved :: MIT License
Classifier: Programming Language :: Python
Classifier: Programming Language :: Python :: 3
Classifier: Programming Language :: Python :: 3.3
Classifier: Programming Language :: Python :: 3.4
Classifier: Programming Language :: Python :: 3.5
